lollypopint/__init__.py
lollypopint-0.2.3.dist-info/LICENSE
lollypopint-0.2.3.dist-info/METADATA
lollypopint-0.2.3.dist-info/WHEEL
lollypopint-0.2.3.dist-info/top_level.txt
lollypopint-0.2.3.dist-info/RECORD
