Metadata-Version: 2.1
Name: lollypopint
Version: 0.2.3
Summary: An extension of the Lollypop Music Player that lets you search for and play music files from the command line
Home-page: https://github.com/Markil3/LollypopInt
Author: Markil3
License: gpl-3.0
Platform: UNKNOWN
